ppui/__init__.py
ppui/base.py
ppui/core.py
ppui-2026.1.24.dist-info/METADATA
ppui-2026.1.24.dist-info/WHEEL
ppui-2026.1.24.dist-info/RECORD
